zbig/__init__.py
zbig/zcache/__init__.py
zbig/zcache/json_cache.py
zbig/zcache/readme.md
zbig/zfile/__init__.py
zbig/zfile/zcsv.py
zbig/zhash/__init__.py
zbig/zhash/args.py
zbig/zprint/__init__.py
zbig/zprint/cn_now.py
zbig/zprint/json_print.py
zbig/zprint/table.py
zbig/ztelegram/__init__.py
zbig/ztelegram/define.py
zbig/ztelegram/send.py
zbig/ztime/__init__.py
zbig/ztime/cn_now.py
zbig-0.1.20.dist-info/METADATA
zbig-0.1.20.dist-info/WHEEL
zbig-0.1.20.dist-info/RECORD
