Metadata-Version: 2.1
Name: zbig
Version: 0.1.20
Summary: Big Zhu Python Utility Library
Author: bigzhu
Author-email: vermiliondun@gmail.com
Requires-Python: >=3.10,<4.0
Classifier: Programming Language :: Python :: 3
Classifier: Programming Language :: Python :: 3.10
Classifier: Programming Language :: Python :: 3.11
Classifier: Programming Language :: Python :: 3.12
Requires-Dist: environs (>=11.0.0,<12.0.0)
Requires-Dist: pyTelegramBotAPI (>=4.16.1,<5.0.0)
Requires-Dist: pytz (>=2024.1,<2025.0)
Requires-Dist: schedule (>=1.2.1,<2.0.0)
